[
  {"name": "137大蒜蒸生蚝", "mainFood": "[0大蒜,0生蚝],", "subFood": "[1花生油,1粉丝,1小葱,1盐,1辣椒,1料酒,1鸡精,1蚝油],", "skill": "蒸", "taste": "蒜香味", "difficulty": "新手尝试"},
{"name": "175菠菜拌扇贝", "mainFood": "[0扇贝,0菠菜],", "subFood": "[1花生油,1大蒜,1盐,1白糖,1味精,1醋],", "skill": "拌", "taste": "蒜香味", "difficulty": "新手尝试"},
{"name": "192蒜蓉油麦菜", "mainFood": "[0油麦菜,0大蒜],", "subFood": "[1花生油,1鸡精,1花椒,1盐],", "skill": "炒", "taste": "蒜香味", "difficulty": "新手尝试"},
{"name": "536脆皮五花肉", "mainFood": "[0猪肉],", "subFood": "[1花生油,1孜然粉,1生姜,1干辣椒,1盐,1白糖,1孜然,1醋,1桂皮],", "skill": "烤", "taste": "蒜香味", "difficulty": "初级入门"},
{"name": "1868蒜蓉蒸海参", "mainFood": "[0海参,0大蒜],", "subFood": "[1花生油,1酱油,1盐,1鸡精],", "skill": "蒸", "taste": "蒜香味", "difficulty": "初级入门"},
{"name": "2651韩式烤肉烧饭", "mainFood": "[0大米,0猪肉],", "subFood": "[1大蒜,1胡萝卜,1鸡蛋,1胡椒,1大葱,1盐,1白糖,1酱油,1料酒,1花生油],", "skill": "炒", "taste": "蒜香味", "difficulty": "未知"},
{"name": "2769凉拌蒜香藤菜", "mainFood": "[0木耳菜,0大蒜],", "subFood": "[1花生油,1蚝油,1盐,1辣椒油,1醋,1酱油],", "skill": "拌", "taste": "蒜香味", "difficulty": "初中水平"},
{"name": "2773蒜泥白肉", "mainFood": "[0猪肉,0大蒜],", "subFood": "[1大葱,1生姜,1花生油,1盐,1酱油,1蚝油],", "skill": "煮", "taste": "蒜香味", "difficulty": "初级入门"},
{"name": "2811蒜蓉小龙虾", "mainFood": "[0小龙虾,0大蒜],", "subFood": "[1花生油,1生姜,1大葱,1干辣椒,1八角,1香叶,1酱油,1酒酿,1盐],", "skill": "煮", "taste": "蒜香味", "difficulty": "中级掌勺"},
{"name": "2835腐乳鸡翅", "mainFood": "[0腐乳,0鸡翅],", "subFood": "[1花生油,1酱油,1盐,1白糖,1大蒜],", "skill": "烩", "taste": "蒜香味", "difficulty": "初中水平"},
{"name": "2883黄瓜火腿炒鸡蛋", "mainFood": "[0黄瓜,0火腿,0鸡蛋],", "subFood": "[1花生油,1大蒜,1大葱,1盐,1青椒],", "skill": "炒", "taste": "蒜香味", "difficulty": "新手尝试"},
{"name": "3269凉拌黄瓜", "mainFood": "[0黄瓜],", "subFood": "[1洋葱,1辣椒油,1黑木耳,1酱油,1大蒜,1大葱,1花生油,1醋,1白糖],", "skill": "拌", "taste": "蒜香味", "difficulty": "新手尝试"},
{"name": "3293电饭煲鸡翅", "mainFood": "[0鸡翅],", "subFood": "[1花生油,1蚝油,1大蒜,1酱油,1料酒,1生姜,1盐,1蜂蜜],", "skill": "其它工艺", "taste": "蒜香味", "difficulty": "初级入门"},
{"name": "3484蒜泥白肉", "mainFood": "[0猪肉,0大蒜],", "subFood": "[1生姜,1黄瓜,1干辣椒,1花椒,1酱油,1辣椒油,1盐,1白糖,1大葱,1花生油],", "skill": "煮", "taste": "蒜香味", "difficulty": "初中水平"},
{"name": "3501秘制蒜蓉牛腩", "mainFood": "[0牛腩,0大蒜],", "subFood": "[1盐,1料酒,1生姜,1花生油,1花椒,1八角,1白芷,1豆瓣酱,1大葱,1酱油,1香菜],", "skill": "炖", "taste": "蒜香味", "difficulty": "初级入门"},
{"name": "3544蚝油生菜", "mainFood": "[0生菜,0蚝油],", "subFood": "[1花生油,1盐,1大蒜,1大葱,1生姜,1白糖,1酱油,1淀粉],", "skill": "炒", "taste": "蒜香味", "difficulty": "新手尝试"},
{"name": "3637紫气东来蒸茄子", "mainFood": "[0茄子],", "subFood": "[1盐,1味精,1花生油,1淀粉,1大蒜,1酱油],", "skill": "蒸", "taste": "蒜香味", "difficulty": "初级入门"},
{"name": "3662蒜仔烧苦瓜", "mainFood": "[0苦瓜],", "subFood": "[1花生油,1大蒜,1盐,1味精,1淀粉],", "skill": "烧", "taste": "蒜香味", "difficulty": "初级入门"},
{"name": "3693客家小封肉", "mainFood": "[0猪肉],", "subFood": "[1花生油,1盐,1生姜,1酱油,1大蒜,1料酒,1白糖],", "skill": "焖", "taste": "蒜香味", "difficulty": "初中水平"},
{"name": "3710茄子拌蒜", "mainFood": "[0茄子],", "subFood": "[1盐,1醋,1鸡精,1大蒜,1酱油,1花生油],", "skill": "拌", "taste": "蒜香味", "difficulty": "初中水平"},
{"name": "3713金蒜芦笋", "mainFood": "[0芦笋,0大蒜],", "subFood": "[1花生油,1盐,1虾米,1大葱,1料酒,1蚝油,1黄油,1白糖],", "skill": "煮", "taste": "蒜香味", "difficulty": "未知"}
]